pyFTS/__init__.py
pyFTS/conf.py
pyFTS/benchmarks/Measures.py
pyFTS/benchmarks/ResidualAnalysis.py
pyFTS/benchmarks/Util.py
pyFTS/benchmarks/__init__.py
pyFTS/benchmarks/arima.py
pyFTS/benchmarks/benchmarks.py
pyFTS/benchmarks/knn.py
pyFTS/benchmarks/naive.py
pyFTS/benchmarks/quantreg.py
pyFTS/common/Composite.py
pyFTS/common/FLR.py
pyFTS/common/FuzzySet.py
pyFTS/common/Membership.py
pyFTS/common/SortedCollection.py
pyFTS/common/Transformations.py
pyFTS/common/Util.py
pyFTS/common/__init__.py
pyFTS/common/flrg.py
pyFTS/common/fts.py
pyFTS/common/tree.py
pyFTS/data/AirPassengers.py
pyFTS/data/Bitcoin.py
pyFTS/data/DowJones.py
pyFTS/data/EURGBP.py
pyFTS/data/EURUSD.py
pyFTS/data/Enrollments.py
pyFTS/data/Ethereum.py
pyFTS/data/GBPUSD.py
pyFTS/data/INMET.py
pyFTS/data/Malaysia.py
pyFTS/data/NASDAQ.py
pyFTS/data/SONDA.py
pyFTS/data/SP500.py
pyFTS/data/TAIEX.py
pyFTS/data/__init__.py
pyFTS/data/artificial.py
pyFTS/data/common.py
pyFTS/data/henon.py
pyFTS/data/logistic_map.py
pyFTS/data/lorentz.py
pyFTS/data/mackey_glass.py
pyFTS/data/rossler.py
pyFTS/data/sunspots.py
pyFTS/distributed/__init__.py
pyFTS/distributed/dispy.py
pyFTS/distributed/spark.py
pyFTS/fcm/Activations.py
pyFTS/fcm/GA.py
pyFTS/fcm/__init__.py
pyFTS/fcm/common.py
pyFTS/fcm/fts.py
pyFTS/hyperparam/Evolutionary.py
pyFTS/hyperparam/GridSearch.py
pyFTS/hyperparam/Util.py
pyFTS/hyperparam/__init__.py
pyFTS/models/__init__.py
pyFTS/models/chen.py
pyFTS/models/cheng.py
pyFTS/models/hofts.py
pyFTS/models/hwang.py
pyFTS/models/ifts.py
pyFTS/models/ismailefendi.py
pyFTS/models/pwfts.py
pyFTS/models/sadaei.py
pyFTS/models/song.py
pyFTS/models/tsaur.py
pyFTS/models/yu.py
pyFTS/models/ensemble/__init__.py
pyFTS/models/ensemble/ensemble.py
pyFTS/models/ensemble/multiseasonal.py
pyFTS/models/incremental/IncrementalEnsemble.py
pyFTS/models/incremental/TimeVariant.py
pyFTS/models/incremental/__init__.py
pyFTS/models/multivariate/FLR.py
pyFTS-1.6.dist-info/DESCRIPTION.rst
pyFTS-1.6.dist-info/METADATA
pyFTS-1.6.dist-info/RECORD
pyFTS-1.6.dist-info/WHEEL
pyFTS-1.6.dist-info/metadata.json
pyFTS-1.6.dist-info/top_level.txt
