Metadata-Version: 2.1
Name: pyFTS
Version: 1.6
Summary: Fuzzy Time Series for Python
Home-page: https://pyfts.github.io/pyFTS/
Author: Petronio Candido L. e Silva
Author-email: petronio.candido@gmail.com
License: UNKNOWN
Download-URL: https://github.com/PYFTS/pyFTS/archive/pkg1.6.tar.gz
Keywords: forecasting,fuzzy time series,fuzzy,time series forecasting
Platform: UNKNOWN
Classifier: Programming Language :: Python :: 3
Classifier: Programming Language :: Python :: 3.4
Classifier: Programming Language :: Python :: 3.5
Classifier: Programming Language :: Python :: 3.6
Classifier: Intended Audience :: Science/Research
Classifier: Intended Audience :: Developers
Classifier: Intended Audience :: Education
Classifier: Topic :: Scientific/Engineering
Classifier: Development Status :: 5 - Production/Stable
